bootloader/__init__.py
bootloader/application.py
bootloader/command_list.py
bootloader/commands/__init__.py
bootloader/commands/clean.py
bootloader/commands/config/__init__.py
bootloader/commands/config/create.py
bootloader/commands/config/download.py
bootloader/commands/config/rename.py
bootloader/commands/config/upload.py
bootloader/commands/download/__init__.py
bootloader/commands/download/tools.py
bootloader/commands/erase.py
bootloader/commands/flash/__init__.py
bootloader/commands/flash/all.py
bootloader/commands/flash/base_flash.py
bootloader/commands/flash/bt121.py
bootloader/commands/flash/config.py
bootloader/commands/flash/ex.py
bootloader/commands/flash/habs.py
bootloader/commands/flash/mn.py
bootloader/commands/flash/re.py
bootloader/commands/flash/xbee.py
bootloader/commands/logo.py
bootloader/commands/show/__init__.py
bootloader/commands/show/base_show.py
bootloader/commands/show/configs.py
bootloader/commands/show/devices.py
bootloader/commands/show/rigids.py
bootloader/commands/show/versions.py
bootloader/exceptions/__init__.py
bootloader/exceptions/exceptions.py
bootloader/main.py
bootloader/utilities/__init__.py
bootloader/utilities/constants.py
bootloader/utilities/help.py
bootloader/utilities/system_utils.py
bootloader-2.3.0.dist-info/LICENSE
bootloader-2.3.0.dist-info/METADATA
bootloader-2.3.0.dist-info/WHEEL
bootloader-2.3.0.dist-info/entry_points.txt
bootloader-2.3.0.dist-info/RECORD
