Metadata-Version: 2.1
Name: bootloader
Version: 2.3.0
Summary: A tool for loading firmware onto Dephy devices.
License: MIT
Author: Jared
Author-email: jcoughlin@dephy.com
Requires-Python: >=3.11,<4.0
Classifier: License :: OSI Approved :: MIT License
Classifier: Programming Language :: Python :: 3
Classifier: Programming Language :: Python :: 3.11
Classifier: Programming Language :: Python :: 3.12
Requires-Dist: cleo (>=2.0.1,<3.0.0)
Requires-Dist: cloudpathlib[s3] (>=0.15.1,<0.16.0)
Requires-Dist: flexsea (>=12.0.4,<13.0.0)
Requires-Dist: pendulum (>=2.1.2,<3.0.0) ; python_version < "3.12"
Requires-Dist: pendulum (>=3.0.0,<4.0.0) ; python_version >= "3.12"
Requires-Dist: pyserial (>=3.5,<4.0)
Requires-Dist: pyyaml (>=6.0,<7.0)
Requires-Dist: semantic-version (>=2.10.0,<3.0.0)
